yolox_backbone/__init__.py
yolox_backbone/models/__init__.py
yolox_backbone/models/backbone.py
yolox_backbone/models/darknet.py
yolox_backbone/models/network_blocks.py
yolox_backbone/models/yolo_fpn.py
yolox_backbone/models/yolo_pafpn.py
yolox_backbone/utils/__init__.py
yolox_backbone/utils/torch_utils.py
yolox_backbone/utils/utils.py
yolox_backbone-0.0.1.9.dist-info/LICENSE
yolox_backbone-0.0.1.9.dist-info/METADATA
yolox_backbone-0.0.1.9.dist-info/WHEEL
yolox_backbone-0.0.1.9.dist-info/top_level.txt
yolox_backbone-0.0.1.9.dist-info/RECORD
