Metadata-Version: 2.1
Name: yolox-backbone
Version: 0.0.1.9
Summary: yolox_backbone is a deep-learning library and is a collection of YOLOX Backbone models.
Home-page: https://github.com/developer0hye/YOLOX-Backbone
Author: Yonghye Kwon
Author-email: developer.0hye@gmail.com
License: Apache
Keywords: yolox
Platform: UNKNOWN
Classifier: Programming Language :: Python :: 3
Classifier: License :: OSI Approved :: Apache Software License
Classifier: Operating System :: OS Independent
Requires-Python: >=3.6
License-File: LICENSE
